README.rst
setup.py
cquauth/__init__.py
cquauth.egg-info/PKG-INFO
cquauth.egg-info/SOURCES.txt
cquauth.egg-info/dependency_links.txt
cquauth.egg-info/requires.txt
cquauth.egg-info/top_level.txt