Metadata-Version: 1.0
Name: cquauth
Version: 0.0.3
Summary: 重庆大学统一认证
Home-page: https://github.com/maxoyed-MS/cqu_auth
Author: maxoyed
Author-email: maxoyed@gmail.com
License: MIT License
Keywords: spider cqu oauth
Platform: any
